odoo/addons/helpdesk_ticket_close_inactive/README.rst
odoo/addons/helpdesk_ticket_close_inactive/__init__.py
odoo/addons/helpdesk_ticket_close_inactive/__manifest__.py
odoo/addons/helpdesk_ticket_close_inactive/data/helpdesk_data.xml
odoo/addons/helpdesk_ticket_close_inactive/i18n/es.po
odoo/addons/helpdesk_ticket_close_inactive/i18n/helpdesk_ticket_close_inactive.pot
odoo/addons/helpdesk_ticket_close_inactive/i18n/it.po
odoo/addons/helpdesk_ticket_close_inactive/models/__init__.py
odoo/addons/helpdesk_ticket_close_inactive/models/helpdesk_ticket_team.py
odoo/addons/helpdesk_ticket_close_inactive/readme/CONFIGURE.md
odoo/addons/helpdesk_ticket_close_inactive/readme/CONTRIBUTORS.md
odoo/addons/helpdesk_ticket_close_inactive/readme/DESCRIPTION.md
odoo/addons/helpdesk_ticket_close_inactive/readme/newsfragments/.gitkeep
odoo/addons/helpdesk_ticket_close_inactive/static/description/icon.png
odoo/addons/helpdesk_ticket_close_inactive/static/description/icon.svg
odoo/addons/helpdesk_ticket_close_inactive/static/description/index.html
odoo/addons/helpdesk_ticket_close_inactive/tests/__init__.py
odoo/addons/helpdesk_ticket_close_inactive/tests/test_ticket_autoclose.py
odoo/addons/helpdesk_ticket_close_inactive/views/helpdesk_ticket_team.xml
odoo_addon_helpdesk_ticket_close_inactive-18.0.1.0.0.2.dist-info/METADATA
odoo_addon_helpdesk_ticket_close_inactive-18.0.1.0.0.2.dist-info/WHEEL
odoo_addon_helpdesk_ticket_close_inactive-18.0.1.0.0.2.dist-info/top_level.txt
odoo_addon_helpdesk_ticket_close_inactive-18.0.1.0.0.2.dist-info/RECORD
