Metadata-Version: 2.1
Name: odoo-addon-helpdesk_ticket_close_inactive
Version: 18.0.1.0.0.2
Requires-Python: >=3.10
Requires-Dist: odoo-addon-helpdesk_mgmt==18.0.*
Requires-Dist: odoo==18.0.*
Summary: Helpdesk Ticket Close Inactive
Home-page: https://github.com/OCA/helpdesk
License: AGPL-3
Author: APSL-Nagarro, Odoo Community Association (OCA)
Author-email: support@odoo-community.org
Classifier: Programming Language :: Python
Classifier: Framework :: Odoo
Classifier: Framework :: Odoo :: 18.0
Classifier: License :: OSI Approved :: GNU Affero General Public License v3
Classifier: Development Status :: 3 - Alpha
